MANIFEST.in
README.markdown
requirements.txt
setup.py
argparsedialog/__init__.py
argparsedialog.egg-info/PKG-INFO
argparsedialog.egg-info/SOURCES.txt
argparsedialog.egg-info/dependency_links.txt
argparsedialog.egg-info/requires.txt
argparsedialog.egg-info/top_level.txt