Metadata-Version: 1.1
Name: argparsedialog
Version: 1.4
Summary: Python library converting argparse to Wizzard using dialog.
Home-page: https://github.com/horejsek/python-argparsedialog
Author: Michal Horejsek
Author-email: horejsekmichal@gmail.com
License: PSF
Platform: UNKNOWN
Classifier: Programming Language :: Python :: 3
Classifier: License :: OSI Approved :: Python Software Foundation License
Classifier: Operating System :: Unix
Classifier: Development Status :: 5 - Production/Stable
Classifier: Intended Audience :: Developers
Classifier: Topic :: Software Development :: Libraries :: Python Modules
